setup.cfg
setup.py
src/hiss/__init__.py
src/hiss/themes/__init__.py
src/hiss/themes/tomorrow.py
src/hiss_themes.egg-info/PKG-INFO
src/hiss_themes.egg-info/SOURCES.txt
src/hiss_themes.egg-info/dependency_links.txt
src/hiss_themes.egg-info/entry_points.txt
src/hiss_themes.egg-info/requires.txt
src/hiss_themes.egg-info/top_level.txt
test/test_themes.py