Metadata-Version: 1.1
Name: hiss-themes
Version: 0.0.1
Summary: Themes for the hiss REPL
Home-page: https://github.com/sixninetynine/hiss-themes
Author: Loren Carvalho
Author-email: me@loren.pizza
License: MIT license
Keywords: hiss
Platform: UNKNOWN
Classifier: License :: OSI Approved :: MIT License
Classifier: Programming Language :: Python :: 2
Classifier: Programming Language :: Python :: 2.7
Classifier: Programming Language :: Python :: 3
Classifier: Programming Language :: Python :: 3.3
Classifier: Programming Language :: Python :: 3.4
Classifier: Programming Language :: Python :: 3.5
